pillow_jxl.libs/libgcc_s-6d2d9dc8.so.1
pillow_jxl.libs/libstdc++-0c867d0f.so.6
pillow_jxl/JpegXLImagePlugin.py
pillow_jxl/__init__.py
pillow_jxl/__init__.pyi
pillow_jxl/pillow_jxl.cpython-311-x86_64-linux-musl.so
pillow_jxl/py.typed
pillow_jxl_plugin-1.3.7.dist-info/METADATA
pillow_jxl_plugin-1.3.7.dist-info/WHEEL
pillow_jxl_plugin-1.3.7.dist-info/licenses/LICENSE
pillow_jxl_plugin-1.3.7.dist-info/RECORD
