Metadata-Version: 2.4
Name: pillow-jxl-plugin
Version: 1.3.7
Classifier: Programming Language :: Rust
Classifier: Programming Language :: Python :: Implementation :: CPython
Classifier: Programming Language :: Python :: Implementation :: PyPy
Requires-Dist: packaging
Requires-Dist: pillow
Requires-Dist: cmake ; extra == 'dev'
Requires-Dist: numpy ; extra == 'dev'
Requires-Dist: openexr ; extra == 'dev'
Requires-Dist: pre-commit ; extra == 'dev'
Requires-Dist: pytest ; extra == 'dev'
Requires-Dist: pyexiv2 ; extra == 'dev'
Requires-Dist: ruff ; extra == 'dev'
Provides-Extra: dev
License-File: LICENSE
Summary: Pillow plugin for JPEG-XL, using Rust for bindings.
Author: Isotr0py
License-Expression: GPL-3.0-or-later
Requires-Python: >=3.9
Project-URL: Homepage, https://github.com/Isotr0py/pillow-jpegxl-plugin
Project-URL: Bug Tracker, https://github.com/Isotr0py/pillow-jpegxl-plugin/issues
Project-URL: Releases, https://github.com/Isotr0py/pillow-jpegxl-plugin/releases
